dfa_samplers/__init__.py
dfa_samplers/dfa_samplers.py
dfa_samplers-0.1.0.dist-info/METADATA
dfa_samplers-0.1.0.dist-info/WHEEL
dfa_samplers-0.1.0.dist-info/licenses/LICENSE
dfa_samplers-0.1.0.dist-info/RECORD
