Metadata-Version: 2.4
Name: dfa-samplers
Version: 0.1.0
Summary: Deterministic Finite Automata (DFA) samplers
License-File: LICENSE
Requires-Python: >=3.12
Requires-Dist: dfa-mutate>=0.1.3
Requires-Dist: dfa>=4.7.1
